<?xml version="1.0" encoding="UTF-8"?>
<objects serializationModel="Studio.02.02.00">
	<object class="AudioFile" id="{7bbc6c38-97dd-417e-9bab-baea7dde78ce}">
		<property name="assetPath">
			<value>Music/RandomMusic/MusicBox-Tremolo_Cm-004.wav</value>
		</property>
		<property name="frequencyInKHz">
			<value>48</value>
		</property>
		<property name="channelCount">
			<value>2</value>
		</property>
		<property name="length">
			<value>6.2394999999999996</value>
		</property>
		<relationship name="masterAssetFolder">
			<destination>{256e74b5-90cf-40a5-812e-e31e90a6d3fd}</destination>
		</relationship>
	</object>
</objects>
