<?xml version="1.0" encoding="UTF-8"?>
<objects serializationModel="Studio.02.02.00">
	<object class="Event" id="{cc798fcb-aa3d-4bf0-87a0-4077a0ef1826}">
		<property name="name">
			<value>Main_Add_HarpXylo</value>
		</property>
		<property name="outputFormat">
			<value>1</value>
		</property>
		<relationship name="folder">
			<destination>{460137cd-c7b7-43ac-9bfa-b30f5fb66caa}</destination>
		</relationship>
		<relationship name="mixer">
			<destination>{6f369ca4-e551-40cf-9183-29bca9d36675}</destination>
		</relationship>
		<relationship name="masterTrack">
			<destination>{59d0ace9-d7c6-4413-a841-55713b44ee60}</destination>
		</relationship>
		<relationship name="mixerInput">
			<destination>{553414ad-3730-4b77-a3c4-363e9727206e}</destination>
		</relationship>
		<relationship name="automatableProperties">
			<destination>{f800af49-8c58-467f-abc8-ac70222a4ccd}</destination>
		</relationship>
		<relationship name="markerTracks">
			<destination>{de35bf72-fbdf-4b61-9bbc-f3e48c9ce228}</destination>
		</relationship>
		<relationship name="groupTracks">
			<destination>{c9755456-b15a-43a8-9b18-f16ff2b058af}</destination>
			<destination>{18703347-0b60-432f-b1b7-5b1e096bfafc}</destination>
		</relationship>
		<relationship name="timeline">
			<destination>{f39e3127-41e7-4be0-846a-d1a042a84517}</destination>
		</relationship>
	</object>
	<object class="EventMixer" id="{6f369ca4-e551-40cf-9183-29bca9d36675}">
		<relationship name="masterBus">
			<destination>{d2b68efa-a7aa-44f3-8097-6b283669669f}</destination>
		</relationship>
	</object>
	<object class="MasterTrack" id="{59d0ace9-d7c6-4413-a841-55713b44ee60}">
		<relationship name="mixerGroup">
			<destination>{d2b68efa-a7aa-44f3-8097-6b283669669f}</destination>
		</relationship>
	</object>
	<object class="MixerInput" id="{553414ad-3730-4b77-a3c4-363e9727206e}">
		<relationship name="effectChain">
			<destination>{6b32f2dc-71ca-4824-a420-0d4eda8a883d}</destination>
		</relationship>
		<relationship name="panner">
			<destination>{917670b0-c5cf-4da5-8506-5e44ffbadf58}</destination>
		</relationship>
	</object>
	<object class="EventAutomatableProperties" id="{f800af49-8c58-467f-abc8-ac70222a4ccd}" />
	<object class="MarkerTrack" id="{de35bf72-fbdf-4b61-9bbc-f3e48c9ce228}" />
	<object class="GroupTrack" id="{c9755456-b15a-43a8-9b18-f16ff2b058af}">
		<relationship name="modules">
			<destination>{a293969c-03ce-4b3c-a985-f3583289e847}</destination>
		</relationship>
		<relationship name="mixerGroup">
			<destination>{1fd6c3a9-3bcb-40e5-a750-eb62c3334037}</destination>
		</relationship>
	</object>
	<object class="GroupTrack" id="{18703347-0b60-432f-b1b7-5b1e096bfafc}">
		<relationship name="modules">
			<destination>{20782175-8962-410e-9df7-ef361de6b16c}</destination>
		</relationship>
		<relationship name="mixerGroup">
			<destination>{7566637f-b19e-417b-95e9-a9a61e2f3ffd}</destination>
		</relationship>
	</object>
	<object class="Timeline" id="{f39e3127-41e7-4be0-846a-d1a042a84517}">
		<relationship name="modules">
			<destination>{a293969c-03ce-4b3c-a985-f3583289e847}</destination>
			<destination>{20782175-8962-410e-9df7-ef361de6b16c}</destination>
		</relationship>
		<relationship name="markers">
			<destination>{225b4cd6-9ff7-4134-a911-5e93825199a4}</destination>
		</relationship>
	</object>
	<object class="EventMixerMaster" id="{d2b68efa-a7aa-44f3-8097-6b283669669f}">
		<relationship name="effectChain">
			<destination>{3029438e-3a76-431d-932e-406145f35a40}</destination>
		</relationship>
		<relationship name="panner">
			<destination>{aec2b0e8-21df-4230-be16-b026897a8c8e}</destination>
		</relationship>
		<relationship name="mixer">
			<destination>{6f369ca4-e551-40cf-9183-29bca9d36675}</destination>
		</relationship>
	</object>
	<object class="MixerBusEffectChain" id="{6b32f2dc-71ca-4824-a420-0d4eda8a883d}">
		<relationship name="effects">
			<destination>{147cef97-6c94-4d4a-949b-4557bc4eb72c}</destination>
		</relationship>
	</object>
	<object class="MixerBusPanner" id="{917670b0-c5cf-4da5-8506-5e44ffbadf58}" />
	<object class="SingleSound" id="{a293969c-03ce-4b3c-a985-f3583289e847}">
		<property name="start">
			<value>0.42857142857142855</value>
		</property>
		<property name="length">
			<value>19.285729166666666</value>
		</property>
		<relationship name="audioFile">
			<destination>{22a468fc-cd74-4818-803b-2380999cda77}</destination>
		</relationship>
	</object>
	<object class="EventMixerGroup" id="{1fd6c3a9-3bcb-40e5-a750-eb62c3334037}">
		<property name="volume">
			<value>-1</value>
		</property>
		<property name="name">
			<value>Audio 1</value>
		</property>
		<relationship name="effectChain">
			<destination>{965fd0b4-3528-4bcf-a3cc-9143e1f05707}</destination>
		</relationship>
		<relationship name="panner">
			<destination>{969bc163-0f51-46da-bc33-77112da6fffd}</destination>
		</relationship>
		<relationship name="output">
			<destination>{d2b68efa-a7aa-44f3-8097-6b283669669f}</destination>
		</relationship>
	</object>
	<object class="SingleSound" id="{20782175-8962-410e-9df7-ef361de6b16c}">
		<property name="length">
			<value>13.285729166666666</value>
		</property>
		<relationship name="audioFile">
			<destination>{0d4b900a-8d7d-4cb7-922a-1f08bf33cfdb}</destination>
		</relationship>
	</object>
	<object class="EventMixerGroup" id="{7566637f-b19e-417b-95e9-a9a61e2f3ffd}">
		<property name="name">
			<value>Audio 2</value>
		</property>
		<relationship name="effectChain">
			<destination>{426eb6ab-e174-4005-bd81-697eafd1dad3}</destination>
		</relationship>
		<relationship name="panner">
			<destination>{f7852f9f-cded-46e6-832d-5da175e7744f}</destination>
		</relationship>
		<relationship name="output">
			<destination>{d2b68efa-a7aa-44f3-8097-6b283669669f}</destination>
		</relationship>
	</object>
	<object class="TempoMarker" id="{225b4cd6-9ff7-4134-a911-5e93825199a4}">
		<property name="position">
			<value>0</value>
		</property>
		<property name="tempo">
			<value>140</value>
		</property>
		<property name="timeSignatureNumerator">
			<value>3</value>
		</property>
		<relationship name="timeline">
			<destination>{f39e3127-41e7-4be0-846a-d1a042a84517}</destination>
		</relationship>
		<relationship name="markerTrack">
			<destination>{de35bf72-fbdf-4b61-9bbc-f3e48c9ce228}</destination>
		</relationship>
	</object>
	<object class="MixerBusEffectChain" id="{3029438e-3a76-431d-932e-406145f35a40}">
		<relationship name="effects">
			<destination>{9b2df55a-6584-461d-b04f-3b2bb7b73a00}</destination>
		</relationship>
	</object>
	<object class="MixerBusPanner" id="{aec2b0e8-21df-4230-be16-b026897a8c8e}" />
	<object class="MixerBusFader" id="{147cef97-6c94-4d4a-949b-4557bc4eb72c}" />
	<object class="MixerBusEffectChain" id="{965fd0b4-3528-4bcf-a3cc-9143e1f05707}">
		<relationship name="effects">
			<destination>{44a232d0-75a8-4337-bac3-bae1b67d7800}</destination>
		</relationship>
	</object>
	<object class="MixerBusPanner" id="{969bc163-0f51-46da-bc33-77112da6fffd}" />
	<object class="MixerBusEffectChain" id="{426eb6ab-e174-4005-bd81-697eafd1dad3}">
		<relationship name="effects">
			<destination>{a6e067b5-130c-49c3-a8b2-74879165f1cd}</destination>
		</relationship>
	</object>
	<object class="MixerBusPanner" id="{f7852f9f-cded-46e6-832d-5da175e7744f}" />
	<object class="MixerBusFader" id="{9b2df55a-6584-461d-b04f-3b2bb7b73a00}" />
	<object class="MixerBusFader" id="{44a232d0-75a8-4337-bac3-bae1b67d7800}" />
	<object class="MixerBusFader" id="{a6e067b5-130c-49c3-a8b2-74879165f1cd}" />
</objects>
